base45/__init__.py
base45/cli.py
base45-0.4.1.dist-info/entry_points.txt
base45-0.4.1.dist-info/LICENSE
base45-0.4.1.dist-info/WHEEL
base45-0.4.1.dist-info/METADATA
base45-0.4.1.dist-info/RECORD
